lswapi/__init__.py
lswapi/httpie.py
lswapi/aio/__init__.py
lswapi/aio/client.py
lswapi/aio/middleware.py
lswapi/aio/oauth.py
lswapi/requests/__init__.py
lswapi/requests/oauth.py
lswapi/requests/session.py
lswapi-0.5.3.dist-info/licenses/LICENSE.txt
lswapi-0.5.3.dist-info/METADATA
lswapi-0.5.3.dist-info/WHEEL
lswapi-0.5.3.dist-info/entry_points.txt
lswapi-0.5.3.dist-info/top_level.txt
lswapi-0.5.3.dist-info/RECORD
