Metadata-Version: 2.4
Name: lswapi
Version: 0.5.3
Summary: a python client library for easy leaseweb api access
Author-email: Nico Di Rocco <n.dirocco@global.leaseweb.com>
License-Expression: Apache-2.0
Project-URL: Homepage, http://developer.leaseweb.com
Project-URL: Issues, https://github.com/nrocco/lswapi
Classifier: Development Status :: 5 - Production/Stable
Classifier: Operating System :: Unix
Classifier: Programming Language :: Python
Classifier: Programming Language :: Python :: 3.9
Classifier: Programming Language :: Python :: 3.10
Classifier: Programming Language :: Python :: 3.11
Classifier: Programming Language :: Python :: 3.12
Classifier: Programming Language :: Python :: 3.13
Classifier: Topic :: Software Development :: Libraries :: Python Modules
Classifier: Topic :: Utilities
Requires-Python: >=3.9
License-File: LICENSE.txt
Provides-Extra: develop
Requires-Dist: flake8; extra == "develop"
Requires-Dist: pytest; extra == "develop"
Requires-Dist: pytest-cov; extra == "develop"
Requires-Dist: requests-mock; extra == "develop"
Provides-Extra: publish
Requires-Dist: build; extra == "publish"
Requires-Dist: twine; extra == "publish"
Provides-Extra: httpie
Requires-Dist: httpie; extra == "httpie"
Provides-Extra: requests
Requires-Dist: requests; extra == "requests"
Provides-Extra: aio
Requires-Dist: aiodns; extra == "aio"
Requires-Dist: aiohttp; extra == "aio"
Dynamic: license-file
